rescreen/__init__.py
rescreen/entrypoint.py
rescreen/gui/__init__.py
rescreen/gui/main_controller.py
rescreen/gui/main_window.py
rescreen/gui/utils.py
rescreen/gui/layouts/__init__.py
rescreen/gui/layouts/main_layout.py
rescreen/gui/preview/__init__.py
rescreen/gui/preview/preview.py
rescreen/gui/preview/preview_item.py
rescreen/lib/__init__.py
rescreen/lib/configuration_manager.py
rescreen/lib/interfaces.py
rescreen/lib/app_settings/__init__.py
rescreen/lib/app_settings/app_settings.py
rescreen/lib/configuration/__init__.py
rescreen/lib/configuration/_utils.py
rescreen/lib/configuration/configuration.py
rescreen/lib/environment/__init__.py
rescreen/lib/environment/detect_environment.py
rescreen/lib/environment/detect_installed_dependencies.py
rescreen/lib/environment/desktop_environment/__init__.py
rescreen/lib/environment/desktop_environment/gnome.py
rescreen/lib/environment/desktop_environment/interface.py
rescreen/lib/environment/desktop_environment/kde.py
rescreen/lib/state/__init__.py
rescreen/lib/state/state.py
rescreen/lib/utils/__init__.py
rescreen/lib/utils/decorator.py
rescreen/lib/utils/misc.py
rescreen/lib/utils/paths.py
rescreen/lib/utils/terminal.py
rescreen/lib/watcher_service/__init__.py
rescreen/lib/watcher_service/service_worker.py
rescreen/lib/watcher_service/watcher_service.py
rescreen/lib/xrandr/__init__.py
rescreen/lib/xrandr/data_structures.py
rescreen/lib/xrandr/settings_structures.py
rescreen/lib/xrandr/utils.py
rescreen/lib/xrandr/xevent_watcher.py
rescreen-1.0.4.dist-info/LICENSE
rescreen-1.0.4.dist-info/METADATA
rescreen-1.0.4.dist-info/WHEEL
rescreen-1.0.4.dist-info/entry_points.txt
rescreen-1.0.4.dist-info/top_level.txt
rescreen-1.0.4.dist-info/RECORD
