Metadata-Version: 2.1
Name: rescreen
Version: 1.0.4
Summary: Screen Manager with fractional scaling support for X11
Home-page: https://github.com/lagmoellertim/rescreen
Author: Tim-Luca Lagmöller
Author-email: mail@lagmoellertim.de
License: MIT License
Classifier: Programming Language :: Python :: 3
Classifier: License :: OSI Approved :: MIT License
Classifier: Operating System :: POSIX :: Linux
License-File: LICENSE
Requires-Dist: pydantic (~=1.9.0)
Requires-Dist: loguru (~=0.6.0)
Requires-Dist: PyYAML (~=6.0)
Requires-Dist: PySide2 (~=5.15.2.1)
